cvplayer/__init__.py
cvplayer/__main__.py
cvplayer/player.py
cvplayer-1.2.0.dist-info/LICENSE
cvplayer-1.2.0.dist-info/METADATA
cvplayer-1.2.0.dist-info/WHEEL
cvplayer-1.2.0.dist-info/entry_points.txt
cvplayer-1.2.0.dist-info/top_level.txt
cvplayer-1.2.0.dist-info/RECORD
