Metadata-Version: 2.1
Name: cvplayer
Version: 1.2.0
Summary: a simple video player based on ffpyplayer and OpenCV
Home-page: https://github.com/addyett/cvplayer
Author: addyett
Author-email: g.aditya2048@gmail.com
License: MIT
Platform: UNKNOWN
Classifier: License :: OSI Approved :: MIT License
Classifier: Programming Language :: Python :: 3.5
Classifier: Programming Language :: Python :: 3.6
Classifier: Programming Language :: Python :: 3.7
Classifier: Programming Language :: Python :: 3.8
Classifier: Operating System :: MacOS
Classifier: Operating System :: MacOS :: MacOS X
Classifier: Operating System :: Microsoft :: Windows :: Windows 10
Classifier: Operating System :: POSIX :: Linux
Classifier: Topic :: Multimedia :: Sound/Audio
Classifier: Topic :: Multimedia :: Sound/Audio :: Players
Classifier: Topic :: Multimedia :: Sound/Audio :: Players :: MP3
License-File: LICENSE
Requires-Dist: opencv-python
Requires-Dist: ffpyplayer
Requires-Dist: numpy
Requires-Dist: pillow
